dashboard_exporter/__init__.py
nrde-0.2.0.dist-info/METADATA
nrde-0.2.0.dist-info/WHEEL
nrde-0.2.0.dist-info/top_level.txt
nrde-0.2.0.dist-info/RECORD
