Metadata-Version: 2.1
Name: nrde
Version: 0.2.0
Summary: A Python client to export a New Relic dashboard PDF or image programmatically.
Home-page: https://github.com/AnthonyBloomer/dashboard-exporter
Author: Anthony Bloomer
Author-email: ant0@protonmail.com
License: MIT
Platform: UNKNOWN
Classifier: License :: OSI Approved :: MIT License
Classifier: Programming Language :: Python
Classifier: Programming Language :: Python :: 3
Classifier: Programming Language :: Python :: 3.6
Classifier: Programming Language :: Python :: Implementation :: CPython
Classifier: Programming Language :: Python :: Implementation :: PyPy
Requires-Python: >=3.6.0
Requires-Dist: requests
